[
  {
    "teamId": 1,
    "name": "Vidya Ravichandran",
    "active": true
  },
  {
    "teamId": 2,
    "name": "Naveen Krishnamurthy",
    "active": true
  },
  {
    "teamId": 3,
    "name": "Navaneetha Krishnan",
    "active": true
  },
  {
    "teamId": 4,
    "name": "Vishnu Ayyappan",
    "active": false
  },
  {
    "teamId": 5,
    "name": "Gowtham Loganathan",
    "active": false
  },
  {
    "teamId": 6,
    "name": "Santhanakrishnan Raghuraman",
    "active": false
  },
  {
    "teamId": 7,
    "name": "Mohamed Fazil",
    "active": true
  },
  {
    "teamId": 8,
    "name": "Gopinath Mariappan",
    "active": false
  },
  {
    "teamId": 9,
    "name": "Girish Verma",
    "active": true
  },
  {
    "teamId": 10,
    "name": "Manojkumar Marimuthu",
    "active": false
  },
  {
    "teamId": 11,
    "name": "Prasath Ravichandran",
    "active": false
  },
  {
    "teamId": 12,
    "name": "Sujatha Mohan",
    "active": true
  },
  {
    "teamId": 13,
    "name": "Krishnakumar Sankarankutty",
    "active": false
  },
  {
    "teamId": 14,
    "name": "Chanchal Jain",
    "active": false
  },
  {
    "teamId": 15,
    "name": "Pratheesh Prabhakaran",
    "active": true
  },
  {
    "teamId": 16,
    "name": "Saranya Sankaran",
    "active": false
  },
  {
    "teamId": 17,
    "name": "Pankajam Krishnamurthy",
    "active": false
  },
  {
    "teamId": 18,
    "name": "Rajalakshmi JagadeshChandran",
    "active": false
  },
  {
    "teamId": 19,
    "name": "Nandhini Natarajan",
    "active": true
  },
  {
    "teamId": 20,
    "name": "Narender Jangid",
    "active": true
  },
  {
    "teamId": 21,
    "name": "Kanimozhi Palanisamy",
    "active": true
  },
  {
    "teamId": 22,
    "name": "Nivedhitha Ramkennedy",
    "active": true
  },{
    "teamId": 23,
    "name": "Varun Nanjan",
    "active": true
  },
  {
    "teamId": 24,
    "name": "Gopalakrishnan R",
    "active": true
  },
  {
    "teamId": 25,
    "name": "Sydulu Gullagunta",
    "active": true
  }
  ,
  {
    "teamId": 25,
    "name": "Pushparaj Mehta",
    "active": true
  } ,
  {
    "teamId": 27,
    "name": "Subhasis Panda",
    "active": true
  },
  {
    "teamId": 28,
    "name": "Sudheer Mavaluru",
    "active": true
  },
  {
    "teamId": 29,
    "name":"Mythili Kannan",
    "active": true
  },
  {
    "teamId": 30,
    "name":"Utkarsh Gupta",
    "active": true
  },
  {
    "teamId": 31,
    "name":"Manojkumar Challagulla",
    "active": true
  },
  {
    "teamId": 32,
    "name":"Rahul Kumar",
    "active": true
  },
  {
    "teamId": 33,
    "name":"VimalRaj",
    "active": true
  },
  {
    "teamId": 34,
    "name":"Varunkumar Reddy Nandyala",
    "active": false
  },
  {
    "teamId": 36,
    "name":"Harisankar Palanisamy",
    "active": true
  },
  {
    "teamId": 37,
    "name":"Abinaya Shanmughan",
    "active": true
  },
  {
    "teamId": 36,
    "name":"Kalaimadhi Anand",
    "active": true
  },
  {
    "teamId": 37,
    "name":"Shona Dhanabalan",
    "active": true
  },
  {
    "teamId": 38,
    "name":"Prabakar R",
    "active": true
  },
  {
    "teamId": 35,
    "name":"Shrihari Sekar",
    "active": false
  },
  {
    "teamId": 36,
    "name":"Yuvakirithika Thangavel",
    "active": true
  },
  {
    "teamId": 37,
    "name":"Rohit Singh",
    "active": true
  },
  {
    "teamId": 38,
    "name":"Arti Uplenchwar",
    "active": true
  }
]